sacremoses/__init__.py
sacremoses/__main__.py
sacremoses/chinese.py
sacremoses/cli.py
sacremoses/corpus.py
sacremoses/indic.py
sacremoses/normalize.py
sacremoses/sent_tokenize.py
sacremoses/subwords.py
sacremoses/tokenize.py
sacremoses/truecase.py
sacremoses/util.py
sacremoses/data/nonbreaking_prefixes/nonbreaking_prefix.ca
sacremoses/data/nonbreaking_prefixes/nonbreaking_prefix.cs
sacremoses/data/nonbreaking_prefixes/nonbreaking_prefix.de
sacremoses/data/nonbreaking_prefixes/nonbreaking_prefix.el
sacremoses/data/nonbreaking_prefixes/nonbreaking_prefix.en
sacremoses/data/nonbreaking_prefixes/nonbreaking_prefix.es
sacremoses/data/nonbreaking_prefixes/nonbreaking_prefix.fi
sacremoses/data/nonbreaking_prefixes/nonbreaking_prefix.fr
sacremoses/data/nonbreaking_prefixes/nonbreaking_prefix.ga
sacremoses/data/nonbreaking_prefixes/nonbreaking_prefix.hu
sacremoses/data/nonbreaking_prefixes/nonbreaking_prefix.is
sacremoses/data/nonbreaking_prefixes/nonbreaking_prefix.it
sacremoses/data/nonbreaking_prefixes/nonbreaking_prefix.lt
sacremoses/data/nonbreaking_prefixes/nonbreaking_prefix.lv
sacremoses/data/nonbreaking_prefixes/nonbreaking_prefix.nl
sacremoses/data/nonbreaking_prefixes/nonbreaking_prefix.pl
sacremoses/data/nonbreaking_prefixes/nonbreaking_prefix.pt
sacremoses/data/nonbreaking_prefixes/nonbreaking_prefix.ro
sacremoses/data/nonbreaking_prefixes/nonbreaking_prefix.ru
sacremoses/data/nonbreaking_prefixes/nonbreaking_prefix.sk
sacremoses/data/nonbreaking_prefixes/nonbreaking_prefix.sl
sacremoses/data/nonbreaking_prefixes/nonbreaking_prefix.sv
sacremoses/data/nonbreaking_prefixes/nonbreaking_prefix.ta
sacremoses/data/nonbreaking_prefixes/nonbreaking_prefix.yue
sacremoses/data/nonbreaking_prefixes/nonbreaking_prefix.zh
sacremoses/data/perluniprops/CJK.txt
sacremoses/data/perluniprops/CJKSymbols.txt
sacremoses/data/perluniprops/Close_Punctuation.txt
sacremoses/data/perluniprops/Currency_Symbol.txt
sacremoses/data/perluniprops/Han.txt
sacremoses_xt-0.0.44.dist-info/LICENSE
sacremoses_xt-0.0.44.dist-info/METADATA
sacremoses_xt-0.0.44.dist-info/WHEEL
sacremoses_xt-0.0.44.dist-info/entry_points.txt
sacremoses_xt-0.0.44.dist-info/top_level.txt
sacremoses_xt-0.0.44.dist-info/RECORD
