Metadata-Version: 2.1
Name: sacremoses-xt
Version: 0.0.44
Summary: SacreMoses (Extended)
Home-page: https://github.com/isi-nlp/sacremoses
Author: UNKNOWN
Author-email: UNKNOWN
License: UNKNOWN
Platform: UNKNOWN
Classifier: Programming Language :: Python :: 3
Classifier: License :: OSI Approved :: MIT License
Classifier: Operating System :: OS Independent
Requires-Dist: regex
Requires-Dist: six
Requires-Dist: click
Requires-Dist: joblib
Requires-Dist: tqdm
